MANIFEST.in
README.rst
setup.py
myyoutube/0.mp4
myyoutube/__init__.py
myyoutube/test.py
myyoutube/uploader.py
myyoutube.egg-info/PKG-INFO
myyoutube.egg-info/SOURCES.txt
myyoutube.egg-info/dependency_links.txt
myyoutube.egg-info/not-zip-safe
myyoutube.egg-info/requires.txt
myyoutube.egg-info/top_level.txt