Metadata-Version: 1.0
Name: myyoutube
Version: 0.3
Summary: Upload videos to youtube using OAuth2.0 and the youtube API
Home-page: https://github.com/fingul/myyoutube
Author: lpbrown999
Author-email: fingul@gmail.com
License: MIT
Keywords: youtube upload uploader
Platform: UNKNOWN
